mystiks/__init__.py
mystiks/__main__.py
mystiks/burp.py
mystiks/mystiks_core.cp310-win_amd64.pyd
mystiks/mystiks_core.cp311-win_amd64.pyd
mystiks/mystiks_core.cp312-win_amd64.pyd
mystiks/mystiks_core.cpython-310-x86_64-linux-gnu.so
mystiks/mystiks_core.cpython-311-x86_64-linux-gnu.so
mystiks/mystiks_core.cpython-312-x86_64-linux-gnu.so
mystiks/patterns.py
mystiks/searcher.py
mystiks/utilities.py
mystiks/findings/__init__.py
mystiks/findings/aws-access-key.py
mystiks/findings/digital-ocean-token.py
mystiks/findings/email.py
mystiks/findings/google-api-token.py
mystiks/findings/json-web-token.py
mystiks/findings/uri.py
mystiks/findings/uuid.py
mystiks/report/report.html
mystiks/report/scripts/censorship.js
mystiks/report/scripts/findings.js
mystiks/report/scripts/utilities.js
mystiks/report/scripts/viewers.js
mystiks/report/stylesheets/custom.css
mystiks/report/vendors/tailwind-3.3.3.js
mystiks/report/vendors/fontawesome-6.4.0/css/all.min.css
mystiks/report/vendors/fontawesome-6.4.0/webfonts/fa-brands-400.ttf
mystiks/report/vendors/fontawesome-6.4.0/webfonts/fa-brands-400.woff2
mystiks/report/vendors/fontawesome-6.4.0/webfonts/fa-regular-400.ttf
mystiks/report/vendors/fontawesome-6.4.0/webfonts/fa-regular-400.woff2
mystiks/report/vendors/fontawesome-6.4.0/webfonts/fa-solid-900.ttf
mystiks/report/vendors/fontawesome-6.4.0/webfonts/fa-solid-900.woff2
mystiks/report/vendors/fontawesome-6.4.0/webfonts/fa-v4compatibility.ttf
mystiks/report/vendors/fontawesome-6.4.0/webfonts/fa-v4compatibility.woff2
mystiks-1.0.7.dist-info/licenses/LICENSE.md
mystiks-1.0.7.dist-info/METADATA
mystiks-1.0.7.dist-info/WHEEL
mystiks-1.0.7.dist-info/entry_points.txt
mystiks-1.0.7.dist-info/top_level.txt
mystiks-1.0.7.dist-info/RECORD
