Metadata-Version: 2.4
Name: mystiks
Version: 1.0.7
Summary: A Python-based, Rust-core secret searching tool 
Home-page: https://github.com/Abacus-Group-RTO/Mystiks
Author: Dennis Carlson
Author-email: dcarlson@abacusgroupllc.com
License: MIT
Classifier: License :: OSI Approved :: MIT License
Classifier: Programming Language :: Python :: 3
License-File: LICENSE.md
Dynamic: author
Dynamic: author-email
Dynamic: classifier
Dynamic: description
Dynamic: description-content-type
Dynamic: home-page
Dynamic: license
Dynamic: license-file
Dynamic: summary
